README.md
setup.py
bakerman/__init__.py
bakerman/errors.py
bakerman.egg-info/PKG-INFO
bakerman.egg-info/SOURCES.txt
bakerman.egg-info/dependency_links.txt
bakerman.egg-info/entry_points.txt
bakerman.egg-info/namespace_packages.txt
bakerman.egg-info/not-zip-safe
bakerman.egg-info/requires.txt
bakerman.egg-info/top_level.txt
bakerman/handler/__init__.py
bakerman/helper/__init__.py
bakerman/plugin/__init__.py
bakerman/plugin/lookup/__init__.py
bakerman/plugin/lookup/alpine_package/__init__.py
bakerman/plugin/lookup/docker_hub/__init__.py
bakerman/plugin/lookup/gitlab_registry/__init__.py
bakerman/plugin/manifest/__init__.py
bakerman/plugin/manifest/json/__init__.py
bakerman/plugin/render/__init__.py
bakerman/plugin/render/jinja2/__init__.py
bakerman/plugin/repo/__init__.py
bakerman/plugin/repo/git/__init__.py